LICENSE
MANIFEST.in
README.rst
jinja2precompiler.py
runtests.py
setup.py
jinja2_precompiler.egg-info/PKG-INFO
jinja2_precompiler.egg-info/SOURCES.txt
jinja2_precompiler.egg-info/dependency_links.txt
jinja2_precompiler.egg-info/entry_points.txt
jinja2_precompiler.egg-info/not-zip-safe
jinja2_precompiler.egg-info/requires.txt
jinja2_precompiler.egg-info/top_level.txt